MANIFEST.in
README.rst
setup.py
django_useful.egg-info/PKG-INFO
django_useful.egg-info/SOURCES.txt
django_useful.egg-info/dependency_links.txt
django_useful.egg-info/not-zip-safe
django_useful.egg-info/top_level.txt
useful/__init__.py
useful/models.py
useful/context_processors/__init__.py
useful/context_processors/settings.py
useful/helpers/__init__.py
useful/helpers/get_object_or_none.py
useful/helpers/json_response.py
useful/tasks/__init__.py
useful/tasks/call_management_command.py
useful/templates/test.html
useful/tests/__init__.py
useful/tests/test_urls.py
useful/tests/context_processors/__init__.py
useful/tests/context_processors/settings.py
useful/tests/helpers/__init__.py
useful/tests/helpers/get_object_or_none.py
useful/tests/helpers/json_response.py
useful/tests/tasks/__init__.py
useful/tests/tasks/call_management_command.py
useful/tests/views/__init__.py
useful/tests/views/extra_context_view.py
useful/views/__init__.py
useful/views/extra_context_view.py