Metadata-Version: 1.1
Name: django-useful
Version: 0.1.2
Summary: Reusable Django snippets
Home-page: http://github.com/yprez/django-useful
Author: Yuri Prezument
Author-email: y@yprez.com
License: ISC
Platform: UNKNOWN
Classifier: Development Status :: 2 - Pre-Alpha
Classifier: Framework :: Django
Classifier: Intended Audience :: Developers
Classifier: Natural Language :: English
Classifier: License :: OSI Approved :: ISC License (ISCL)
Classifier: Programming Language :: Python
Classifier: Programming Language :: Python :: 2.6
Classifier: Programming Language :: Python :: 2.7
